{
  "$id": "http://gov.uk/schema/v1.0.0/definition/html_attributes",
  "_name": "definition.html_attributes",
  "title": "HTML attributes definition",
  "description": "Additional HTML values to set on instances",
  "type": "object",
  "properties": {
    "id": {
      "title": "HTML id",
      "description": "Additional HTML id to apply to instance - only use as a last resort, to target a specific element on the page",
      "type": "string",
      "category": [
        "html_attributes"
      ]
    },
    "classes": {
      "title": "Classes",
      "description": "Additional HTML classes to apply to instance - to add more than one, separate with a space",
      "type": "string",
      "content": true,
      "category": [
        "html_attributes"
      ]
    },
    "attributes": {
      "title": "Attributes",
      "description": "Additional HTML attributes to apply to instance - Enter the attributes as JSON",
      "type": "object",
      "category": [
        "html_attributes"
      ]
    }
  },
  "category": [
    "definition"
  ]
}
